PyMLRS/Mep_panel.py
PyMLRS/Rextractor.py
PyMLRS/Threshold.xlsx
PyMLRS/__init__.py
PyMLRS/model.pkl
PyMLRS-0.0.4.dist-info/LICENCE.txt
PyMLRS-0.0.4.dist-info/METADATA
PyMLRS-0.0.4.dist-info/WHEEL
PyMLRS-0.0.4.dist-info/top_level.txt
PyMLRS-0.0.4.dist-info/RECORD
